bqemulatormanager/__init__.py
bqemulatormanager/emulator.py
bqemulatormanager/manager.py
bqemulatormanager/schema.py
bqemulatormanager-0.2.3.dist-info/METADATA
bqemulatormanager-0.2.3.dist-info/WHEEL
bqemulatormanager-0.2.3.dist-info/RECORD
