Metadata-Version: 2.1
Name: bqemulatormanager
Version: 0.2.3
Summary: bqemulatormanager is a wrapper of bigquery-emulator which provides us BigQuery mock working in local machine.
Author: gyuta
Author-email: kuroshiba0408@gmail.com
Requires-Python: >=3.8,<4
Classifier: Programming Language :: Python :: 3
Classifier: Programming Language :: Python :: 3.8
Classifier: Programming Language :: Python :: 3.9
Classifier: Programming Language :: Python :: 3.10
Classifier: Programming Language :: Python :: 3.11
Classifier: Programming Language :: Python :: 3.12
Classifier: Programming Language :: Python :: 3.13
Requires-Dist: db-dtypes (>=1.0.0,<2.0.0)
Requires-Dist: google-auth (>=2.17.2,<3.0.0)
Requires-Dist: google-cloud-bigquery (>=2.34.4)
Requires-Dist: psutil (>=5.0.0,<6.0.0)
Requires-Dist: pyyaml
